[
    {
        "Id": "3001",
        "Name": "\u683C\u6805",
        "posX": -500.0,
        "posY": 10.1,
        "posZ": -497.5,
        "rotateY": -90.0
    },
    {
        "Id": "3002",
        "Name": "\u65CB\u6D41\u6C89\u7802\u6C60",
        "posX": -500.0,
        "posY": 10.1,
        "posZ": -440.75,
        "rotateY": -90.0
    },
    {
        "Id": "3003",
        "Name": "\u521D\u6C89\u6C60",
        "posX": -495.0,
        "posY": 10.1,
        "posZ": -406.5,
        "rotateY": 90.0
    },
    {
        "Id": "3004",
        "Name": "\u751F\u7269\u6C60",
        "posX": -495.0,
        "posY": 10.1,
        "posZ": -482.5,
        "rotateY": 90.0
    },
    {
        "Id": "3005",
        "Name": "\u4E8C\u6C89\u6C60",
        "posX": -417.0,
        "posY": 10.1,
        "posZ": -477.6,
        "rotateY": 90.0
    },
    {
        "Id": "3006",
        "Name": "\u6DF1\u5E8A\u6EE4\u6C60",
        "posX": -417.0,
        "posY": 10.1,
        "posZ": -427.9,
        "rotateY": 90.0
    },
    {
        "Id": "3007",
        "Name": "\u7D2B\u5916\u7EBF\u6D88\u6BD2\u6CF5",
        "posX": -401.0,
        "posY": 10.1,
        "posZ": -382.0,
        "rotateY": 0.0
    },
    {
        "Id": "3008",
        "Name": "\u9F13\u98CE\u673A\u623F",
        "posX": -422.0,
        "posY": 10.1,
        "posZ": -484.5,
        "rotateY": -90.0
    },
    {
        "Id": "3009",
        "Name": "\u677F\u6846\u538B\u6EE4\u673A",
        "posX": -363.0,
        "posY": 10.1,
        "posZ": -518.0,
        "rotateY": 180.0
    }
]
